pykbart/__init__.py
pykbart/constants.py
pykbart/exceptions.py
pykbart/holdings.py
pykbart/kbartrecord.py
pykbart/reader.py
pykbart/writer.py
pykbart-0.1.0a1.dist-info/DESCRIPTION.rst
pykbart-0.1.0a1.dist-info/METADATA
pykbart-0.1.0a1.dist-info/RECORD
pykbart-0.1.0a1.dist-info/WHEEL
pykbart-0.1.0a1.dist-info/metadata.json
pykbart-0.1.0a1.dist-info/top_level.txt
